hdl21/__init__.py
hdl21/connect.py
hdl21/elab.py
hdl21/generator.py
hdl21/generators.py
hdl21/instance.py
hdl21/instantiable.py
hdl21/interface.py
hdl21/module.py
hdl21/netlist/__init__.py
hdl21/params.py
hdl21/primitives.py
hdl21/proto/__init__.py
hdl21/proto/circuit.proto
hdl21/proto/circuit_pb2.py
hdl21/proto/from_proto.py
hdl21/proto/readme.md
hdl21/proto/to_proto.py
hdl21/signal.py
hdl21/tests/__init__.py
hdl21/tests/test_hdl21.py
hdl21/walker.py
hdl21-0.1.1.dist-info/LICENSE
hdl21-0.1.1.dist-info/WHEEL
hdl21-0.1.1.dist-info/METADATA
hdl21-0.1.1.dist-info/RECORD
