Metadata-Version: 2.1
Name: hdl21
Version: 0.1.1
Summary: Hardware Description Library
License: BSD-3-Clause
Author: Dan Fritchman
Author-email: dan@fritch.mn
Requires-Python: >=3.7,<4.0
Classifier: License :: OSI Approved :: BSD License
Classifier: Programming Language :: Python :: 3
Classifier: Programming Language :: Python :: 3.7
Classifier: Programming Language :: Python :: 3.8
Classifier: Programming Language :: Python :: 3.9
Requires-Dist: protobuf (>=3.17.0,<4.0.0)
Requires-Dist: pydantic (>=1.8.2,<2.0.0)
